PygameXtras/__init__.py
PygameXtras/src/__init__.py
PygameXtras/src/classes/Bar.py
PygameXtras/src/classes/Button.py
PygameXtras/src/classes/C.py
PygameXtras/src/classes/Collisions.py
PygameXtras/src/classes/Colors.py
PygameXtras/src/classes/CustomTemplate.py
PygameXtras/src/classes/Entity.py
PygameXtras/src/classes/Entry.py
PygameXtras/src/classes/Function.py
PygameXtras/src/classes/Functions.py
PygameXtras/src/classes/Keyboard.py
PygameXtras/src/classes/Label.py
PygameXtras/src/classes/Messagebox.py
PygameXtras/src/classes/OneClickManager.py
PygameXtras/src/classes/PSController.py
PygameXtras/src/classes/Paragraph.py
PygameXtras/src/classes/PerformanceGraph.py
PygameXtras/src/classes/PlayStationVectorGraphics/__init__.py
PygameXtras/src/classes/PlayStationVectorGraphics/psvg.py
PygameXtras/src/classes/PlayStationVectorGraphics/psvg_util.py
PygameXtras/src/classes/PopupMessage.py
PygameXtras/src/classes/RandomClasses.py
PygameXtras/src/classes/RetroController.py
PygameXtras/src/classes/ScrollableButtonList.py
PygameXtras/src/classes/Spritesheet.py
PygameXtras/src/classes/Table.py
PygameXtras/src/classes/__init__.py
PygameXtras/src/fonts/__init__.py
PygameXtras/src/fonts/arial.ttf
PygameXtras/src/fonts/arialnova.ttf
PygameXtras/src/fonts/bahnschrift.ttf
PygameXtras/src/fonts/baskvill.ttf
PygameXtras/src/fonts/bauhs93.ttf
PygameXtras/src/fonts/caladea.ttf
PygameXtras/src/fonts/calibri.ttf
PygameXtras/src/fonts/califr.ttf
PygameXtras/src/fonts/calist.ttf
PygameXtras/src/fonts/candara.ttf
PygameXtras/src/fonts/carlito.ttf
PygameXtras/src/fonts/castelar.ttf
PygameXtras/src/fonts/centaur.ttf
PygameXtras/src/fonts/century.ttf
PygameXtras/src/fonts/chiller.ttf
PygameXtras/src/fonts/comic.ttf
PygameXtras/src/fonts/consola.ttf
PygameXtras/src/fonts/constan.ttf
PygameXtras/src/fonts/coprgtl.ttf
PygameXtras/src/fonts/corbel.ttf
PygameXtras/src/fonts/cour.ttf
PygameXtras/src/fonts/dejavusans.ttf
PygameXtras/src/fonts/elephnt.ttf
PygameXtras/src/fonts/erasbd.ttf
pygamextras-1.3.5.dist-info/LICENSE.txt
pygamextras-1.3.5.dist-info/METADATA
pygamextras-1.3.5.dist-info/WHEEL
pygamextras-1.3.5.dist-info/RECORD
