Metadata-Version: 2.3
Name: PygameXtras
Version: 1.3.5
Summary: Labels, Buttons and much more for pygame
License: MIT
Author: marcelm9
Author-email: marcel.menzel09@gmail.com
Requires-Python: >=3.11,<4.0
Classifier: License :: OSI Approved :: MIT License
Classifier: Programming Language :: Python :: 3
Classifier: Programming Language :: Python :: 3.11
Classifier: Programming Language :: Python :: 3.12
Classifier: Programming Language :: Python :: 3.13
Requires-Dist: pygame-ce (>=2.4.0,<3.0.0)
Project-URL: Repository, https://github.com/marcelm9/PygameXtras.git
